foo_package/__init__.py
stable_world_example_package-1.0.dist-info/DESCRIPTION.rst
stable_world_example_package-1.0.dist-info/METADATA
stable_world_example_package-1.0.dist-info/RECORD
stable_world_example_package-1.0.dist-info/WHEEL
stable_world_example_package-1.0.dist-info/metadata.json
stable_world_example_package-1.0.dist-info/top_level.txt
